odoo/addons/web_dialog_size/README.rst
odoo/addons/web_dialog_size/__init__.py
odoo/addons/web_dialog_size/__manifest__.py
odoo/addons/web_dialog_size/i18n/web_dialog_size.pot
odoo/addons/web_dialog_size/models/__init__.py
odoo/addons/web_dialog_size/models/ir_config_parameter.py
odoo/addons/web_dialog_size/readme/CONFIGURATION.rst
odoo/addons/web_dialog_size/readme/CONTRIBUTORS.rst
odoo/addons/web_dialog_size/readme/DESCRIPTION.rst
odoo/addons/web_dialog_size/static/description/icon.png
odoo/addons/web_dialog_size/static/description/index.html
odoo/addons/web_dialog_size/static/src/css/web_dialog_size.css
odoo/addons/web_dialog_size/static/src/js/web_dialog_size.js
odoo/addons/web_dialog_size/static/src/xml/web_dialog_size.xml
odoo/addons/web_dialog_size/templates/assets.xml
odoo11_addon_web_dialog_size-11.0.1.0.4.dist-info/METADATA
odoo11_addon_web_dialog_size-11.0.1.0.4.dist-info/WHEEL
odoo11_addon_web_dialog_size-11.0.1.0.4.dist-info/top_level.txt
odoo11_addon_web_dialog_size-11.0.1.0.4.dist-info/RECORD
